toll/__init__.py
toll/compat.py
toll/config.py
toll/main.py
toll/run.py
toll/test_config.py
toll/test_main.py
toll/test_run.py
toll/testing.py
toll/fixtures/bad/bad.py
toll/fixtures/bad/setup.py
toll/fixtures/fine/fine.py
toll/fixtures/fine/setup.py
toll/fixtures/finetoo/finetoo.py
toll/fixtures/finetoo/setup.py
toll-4.2.1.dist-info/LICENSE.txt
toll-4.2.1.dist-info/METADATA
toll-4.2.1.dist-info/WHEEL
toll-4.2.1.dist-info/entry_points.txt
toll-4.2.1.dist-info/top_level.txt
toll-4.2.1.dist-info/RECORD
