Metadata-Version: 2.1
Name: toll
Version: 4.2.1
Summary: poor man's integration testing
Home-page: https://github.com/icemac/toll
Author: Michael Howitz
Author-email: icemac@gmx.net
License: MIT
Keywords: test testing offline integration multiple packages
Platform: UNKNOWN
Classifier: Development Status :: 4 - Beta
Classifier: Environment :: Console
Classifier: Intended Audience :: Developers
Classifier: License :: OSI Approved :: MIT License
Classifier: Natural Language :: English
Classifier: Operating System :: OS Independent
Classifier: Programming Language :: Python :: 2
Classifier: Programming Language :: Python :: 2.7
Classifier: Programming Language :: Python :: 3
Classifier: Programming Language :: Python :: 3.5
Classifier: Programming Language :: Python :: 3.6
Classifier: Programming Language :: Python :: 3.7
Classifier: Programming Language :: Python :: 3.8
Classifier: Programming Language :: Python :: Implementation :: CPython
Classifier: Programming Language :: Python :: Implementation :: PyPy
Classifier: Topic :: Software Development :: Testing
Classifier: Topic :: Software Development :: Quality Assurance
Classifier: Topic :: Utilities
Requires-Dist: colorama
Requires-Dist: backports.shutil-get-terminal-size ; python_version < "3.4"
Requires-Dist: configparser (<5) ; python_version < "3.5"
Provides-Extra: test
Requires-Dist: pytest (>=3) ; extra == 'test'
Requires-Dist: mock ; (python_version < "3.3") and extra == 'test'
